{
    "category" : {
        "fruit" :  {
            "raisin" : {
                "data" : [
                   {
                        "name" : "fruit 1",
                        "image" : "images/fruit1.jpg",
                        "description" : "lorem ipsum"
                    }
                ]
            },
            "tomate" : {
                "data" : [
                    {
                        "name" : "fruit 2",
                        "image" : "images/fruit2.JPG",
                        "description" : "lorem ipsum"
                    }
                ]
            }
        },
        "vegetable" :{
            "riz" : {
                "data" : [
                    {
                        "name" : "vegetable 1",
                        "image" : "images/vegetable1.jpg",
                        "description" : "lorem ipsum"
                    }
                ]
            },
            "haricot" : {
                "data" : [
                    {
                        "name" : "vegetable 2",
                        "image" : "images/vegetable2.jpg",
                        "description" : "lorem ipsum"
                    }
                ]
            }
        }
    }
}
